mlnods/__init__.py
mlnods/__main__.py
mlnods/cli.py
mlnods/helpers.py
mlnods/mlnods.py
mlnods/run.py
mlnods/legacy/m8ToRdb.pl
mlnods/legacy/treeSort.pl
mlnods-1.3.dist-info/LICENSE.md
mlnods-1.3.dist-info/METADATA
mlnods-1.3.dist-info/WHEEL
mlnods-1.3.dist-info/entry_points.txt
mlnods-1.3.dist-info/top_level.txt
mlnods-1.3.dist-info/RECORD
