Metadata-Version: 2.1
Name: mlnods
Version: 1.3
Summary: a python package to split machine learning data sets using graph partitioning
Home-page: https://bitbucket.org/bromberglab/mlnods
Author: Yana Bromberg, Maximilian Miller
Author-email: mmiller@bromberglab.com
License: NPOSL-3.0
Project-URL: Bug Tracker, https://bitbucket.org/bromberglab/mlnods/issues
Project-URL: Documentation, https://bitbucket.org/bromberglab/mlnods/wiki/docs
Project-URL: Source Code, https://bitbucket.org/bromberglab/mlnods
Keywords: graph partition,graph analysis,cross-validation dataset
Platform: UNKNOWN
Classifier: Development Status :: 5 - Production/Stable
Classifier: Intended Audience :: Science/Research
Classifier: Topic :: Scientific/Engineering :: Bio-Informatics
Classifier: Programming Language :: Python :: 3
Classifier: Programming Language :: Python :: 3.6
Classifier: Programming Language :: Python :: 3.7
Classifier: Programming Language :: Python :: 3.8
Classifier: Natural Language :: English
Classifier: Operating System :: OS Independent
Requires-Python: >=3.6
